ambivalent/__about__.py
ambivalent/__init__.py
ambivalent/build_example_plots.py
ambivalent/core.py
ambivalent/utils.py
ambivalent/stylefiles/ambivalent.mplstyle
ambivalent/stylefiles/minimal-new.mplstyle
ambivalent/stylefiles/minimal.mplstyle
ambivalent/stylefiles/opinionated_fsc.mplstyle
ambivalent/stylefiles/opinionated_j.mplstyle
ambivalent/stylefiles/opinionated_m.mplstyle
ambivalent/stylefiles/opinionated_min.mplstyle
ambivalent/stylefiles/opinionated_rc.mplstyle
ambivalent/stylefiles/opinionated_sg.mplstyle
ambivalent/stylefiles/opinionated_tw.mplstyle
ambivalent/stylefiles/opinions.mplstyle
ambivalent-0.3.0.dist-info/METADATA
ambivalent-0.3.0.dist-info/WHEEL
ambivalent-0.3.0.dist-info/RECORD
