Metadata-Version: 2.3
Name: ambivalent
Version: 0.3.0
Summary: Minimal, beautiful (+ highly-customizable) styles for Matplotlib.
Project-URL: Documentation, https://github.com/saforem2/ambivalent
Project-URL: Issues, https://github.com/saforem2/ambivalent/issues
Project-URL: Source, https://github.com/saforem2/ambivalent
Author-email: Sam Foreman <saforem2@gmail.com>
License-Expression: MIT
Classifier: Development Status :: 4 - Beta
Classifier: Programming Language :: Python
Classifier: Programming Language :: Python :: 3.8
Classifier: Programming Language :: Python :: 3.9
Classifier: Programming Language :: Python :: 3.10
Classifier: Programming Language :: Python :: 3.11
Classifier: Programming Language :: Python :: Implementation :: CPython
Classifier: Programming Language :: Python :: Implementation :: PyPy
Requires-Python: >=3.8
Requires-Dist: colormaps
Requires-Dist: matplotlib
Requires-Dist: requests
Requires-Dist: seaborn
Provides-Extra: dev
Requires-Dist: ipython; extra == 'dev'
Requires-Dist: neovim; extra == 'dev'
Requires-Dist: nodejs; extra == 'dev'
Requires-Dist: ptipython; extra == 'dev'
Requires-Dist: pudb; extra == 'dev'
Requires-Dist: pynvim; extra == 'dev'
Requires-Dist: pyproject-flake8; extra == 'dev'
Requires-Dist: ruff; extra == 'dev'
Requires-Dist: ruff-lsp; extra == 'dev'
